mitmproxy_windows/LICENSE
mitmproxy_windows/WINDIVERT_VERSION
mitmproxy_windows/WinDivert.dll
mitmproxy_windows/WinDivert.lib
mitmproxy_windows/WinDivert64.sys
mitmproxy_windows/__init__.py
mitmproxy_windows/windows-redirector.exe
mitmproxy_windows-0.12.6.dist-info/METADATA
mitmproxy_windows-0.12.6.dist-info/WHEEL
mitmproxy_windows-0.12.6.dist-info/RECORD
