Metadata-Version: 2.4
Name: mitmproxy-windows
Version: 0.12.6
Project-URL: Source, https://github.com/mitmproxy/mitmproxy-rs
License-Expression: LGPL-3.0-or-later
Requires-Python: >=3.12
